lightbrow/__init__.py
lightbrow/browsers/__init__.py
lightbrow/browsers/s3browser.py
lightbrow/connectors/__init__.py
lightbrow/connectors/base.py
lightbrow/connectors/s3connector.py
lightbrow/search_engines/__init__.py
lightbrow/search_engines/simple_seach.py
lightbrow/tests/test_simple.py
lightbrow/utils/__init__.py
lightbrow-0.1.0.dist-info/licenses/LICENSE
lightbrow-0.1.0.dist-info/METADATA
lightbrow-0.1.0.dist-info/WHEEL
lightbrow-0.1.0.dist-info/top_level.txt
lightbrow-0.1.0.dist-info/RECORD
