Metadata-Version: 2.4
Name: lightbrow
Version: 0.1.0
Summary: A Fast and S3 or other cloud storage compatible browser application
Author-email: FlowFoundation Team <lytran14789@gmail.com>
License: MIT
Project-URL: Homepage, https://github.com/FlowFoundation/lightbrow
Project-URL: Bug Tracker, https://github.com/FlowFoundation/lightbrow/issues
Classifier: Programming Language :: Python :: 3
Classifier: Programming Language :: Python :: 3.9
Classifier: Programming Language :: Python :: 3.10
Classifier: Programming Language :: Python :: 3.11
Classifier: License :: OSI Approved :: MIT License
Classifier: Operating System :: OS Independent
Classifier: Development Status :: 4 - Beta
Classifier: Intended Audience :: Developers
Classifier: Intended Audience :: Science/Research
Classifier: Topic :: Scientific/Engineering :: Visualization
Requires-Python: >=3.9
License-File: LICENSE
Requires-Dist: dash>=3.0.0
Requires-Dist: dash_mantine_components==1.3.0
Requires-Dist: dash-iconify==0.1.2
Requires-Dist: boto3>=1.38.0
Requires-Dist: jupyter-dash>=0.4.2
Requires-Dist: ipython>=7.0.0
Requires-Dist: pandas>=1.0.0
Requires-Dist: pyperclip>=1.8.0
Provides-Extra: dev
Requires-Dist: pytest>=7.0.0; extra == "dev"
Requires-Dist: build; extra == "dev"
Requires-Dist: twine; extra == "dev"
Dynamic: license-file
